{
    "description": {
        "columns": [
            "name",
            "title",
            "value",
            "type",
            "sort_order",
            "is_hidden",
            "precision"
        ],
        "data": [
            [
                "SECID",
                "Код ценной бумаги",
                "XS0191754729",
                "string",
                1,
                0,
                null
            ],
            [
                "NAME",
                "Полное наименование",
                "GAZ CAPITAL SA 8.625 28/04/34",
                "string",
                3,
                0,
                null
            ],
            [
                "SHORTNAME",
                "Краткое наименование",
                "GAZPR-34",
                "string",
                4,
                0,
                null
            ],
            [
                "ISIN",
                "ISIN код",
                "XS0191754729",
                "string",
                6,
                0,
                null
            ],
            [
                "ISSUEDATE",
                "Дата начала торгов",
                "2014-10-14",
                "date",
                7,
                0,
                null
            ],
            [
                "MATDATE",
                "Дата погашения",
                "2034-04-28",
                "date",
                8,
                0,
                null
            ],
            [
                "INITIALFACEVALUE",
                "Первоначальная номинальная стоимость",
                "1000",
                "number",
                10,
                0,
                2
            ],
            [
                "FACEUNIT",
                "Валюта номинала",
                "USD",
                "string",
                11,
                0,
                null
            ],
            [
                "LATNAME",
                "Английское наименование",
                "GAZ CAPITAL SA 8.62500 28/04/3",
                "string",
                12,
                1,
                null
            ],
            [
                "STARTDATEMOEX",
                "Дата начала торгов на Московской Бирже",
                "2023-03-27",
                "date",
                13,
                0,
                null
            ],
            [
                "DAYSTOREDEMPTION",
                "Дней до погашения",
                "3487",
                "number",
                25,
                0,
                0
            ],
            [
                "ISSUESIZE",
                "Объем выпуска",
                "1200000",
                "number",
                26,
                0,
                0
            ],
            [
                "FACEVALUE",
                "Номинальная стоимость",
                "1000",
                "number",
                27,
                0,
                2
            ],
            [
                "ISQUALIFIEDINVESTORS",
                "Бумаги для квалифицированных инвесторов",
                "1",
                "boolean",
                28,
                0,
                0
            ],
            [
                "QUALINVESTORGROUP",
                "Категория квалифицированного инвестора",
                "Все",
                "string",
                29,
                0,
                null
            ],
            [
                "COUPONFREQUENCY",
                "Периодичность выплаты купона в год",
                "2",
                "number",
                30,
                0,
                0
            ],
            [
                "COUPONDATE",
                "Дата выплаты купона",
                "2024-10-28",
                "date",
                31,
                0,
                null
            ],
            [
                "COUPONPERCENT",
                "Ставка купона, %",
                "8.625",
                "number",
                32,
                0,
                3
            ],
            [
                "COUPONVALUE",
                "Сумма купона, в валюте номинала",
                "43.125",
                "number",
                33,
                0,
                3
            ],
            [
                "TYPENAME",
                "Вид/категория ценной бумаги",
                "Корпоративная облигация",
                "string",
                9000,
                0,
                null
            ],
            [
                "GROUP",
                "Код типа инструмента",
                "stock_bonds",
                "string",
                9001,
                1,
                null
            ],
            [
                "TYPE",
                "Тип бумаги",
                "corporate_bond",
                "string",
                10000,
                1,
                null
            ],
            [
                "GROUPNAME",
                "Типа инструмента",
                "Облигации",
                "string",
                10011,
                1,
                null
            ],
            [
                "EMITTER_ID",
                "Код эмитента",
                "7202",
                "number",
                11000,
                1,
                null
            ]
        ]
    },
    "boards": {
        "columns": [
            "secid",
            "boardid",
            "title",
            "board_group_id",
            "market_id",
            "market",
            "engine_id",
            "engine",
            "is_traded",
            "decimals",
            "history_from",
            "history_till",
            "listed_from",
            "listed_till",
            "is_primary",
            "currencyid"
        ],
        "data": [
            [
                "XS0191754729",
                "TQCB",
                "Т+: Облигации - безадрес.",
                58,
                2,
                "bonds",
                1,
                "stock",
                0,
                4,
                "2022-03-09",
                "2022-10-26",
                "2022-03-09",
                "2022-10-26",
                0,
                "RUB"
            ],
            [
                "XS0191754729",
                "TQOD",
                "Т+: Облигации (USD) - безадрес.",
                193,
                2,
                "bonds",
                1,
                "stock",
                0,
                4,
                "2016-01-25",
                "2022-10-26",
                "2016-01-25",
                "2022-10-26",
                0,
                "USD"
            ],
            [
                "XS0191754729",
                "EQEU",
                "Облигации (USD) - безадрес.",
                67,
                2,
                "bonds",
                1,
                "stock",
                0,
                4,
                "2014-10-14",
                "2016-01-22",
                "2014-10-14",
                "2016-01-22",
                0,
                "USD"
            ],
            [
                "XS0191754729",
                "LIQB",
                "Продажа обеспечения бирж.рынок - безадрес.",
                120,
                36,
                "mamc",
                1,
                "stock",
                0,
                4,
                "2022-04-01",
                "2022-04-01",
                "2018-05-21",
                "2023-04-10",
                0,
                null
            ],
            [
                "XS0191754729",
                "RPEY",
                "РЕПО в ин.валюте (CNY) - адрес.",
                2,
                3,
                "repo",
                1,
                "stock",
                0,
                6,
                null,
                null,
                "2022-09-26",
                "2022-10-26",
                0,
                "CNY"
            ],
            [
                "XS0191754729",
                "RPEU",
                "РЕПО в ин. валюте (USD) - адрес.",
                94,
                3,
                "repo",
                1,
                "stock",
                0,
                6,
                "2016-04-01",
                "2022-01-26",
                "2014-10-14",
                "2022-10-26",
                0,
                "USD"
            ],
            [
                "XS0191754729",
                "RPEO",
                "РЕПО в ин. валюте (EUR) - адрес.",
                90,
                3,
                "repo",
                1,
                "stock",
                0,
                6,
                "2018-08-27",
                "2019-12-20",
                "2014-10-27",
                "2022-10-26",
                0,
                "EUR"
            ],
            [
                "XS0191754729",
                "SOTC",
                "Репортинг внебиржевых сделок (6264-У)",
                71,
                29,
                "otc",
                1,
                "stock",
                0,
                5,
                "2016-03-01",
                "2022-10-07",
                "2016-03-01",
                "2022-10-07",
                0,
                null
            ],
            [
                "XS0191754729",
                "PSOB",
                "РПС: Облигации - адрес.",
                284,
                4,
                "ndm",
                1,
                "stock",
                0,
                4,
                "2022-04-06",
                "2022-10-21",
                "2022-03-09",
                "2022-10-26",
                0,
                "RUB"
            ],
            [
                "XS0191754729",
                "PSEU",
                "РПС: Облигации (USD) - адрес.",
                285,
                4,
                "ndm",
                1,
                "stock",
                0,
                4,
                "2015-10-29",
                "2022-06-10",
                "2014-10-14",
                "2022-10-26",
                0,
                "USD"
            ],
            [
                "XS0191754729",
                "PSBB",
                "Выкуп - адрес.",
                108,
                4,
                "ndm",
                1,
                "stock",
                0,
                4,
                "2022-10-11",
                "2023-04-05",
                "2022-10-11",
                "2023-04-05",
                0,
                "RUB"
            ],
            [
                "XS0191754729",
                "OTCU",
                "Анонимный РПС (USD) - адрес.",
                203,
                4,
                "ndm",
                1,
                "stock",
                0,
                4,
                null,
                null,
                "2020-04-24",
                "2022-10-26",
                0,
                "USD"
            ],
            [
                "XS0191754729",
                "PTOB",
                "РПС с ЦК: Облигации - адрес.",
                282,
                4,
                "ndm",
                1,
                "stock",
                0,
                4,
                "2022-03-30",
                "2022-09-16",
                "2022-03-09",
                "2022-10-26",
                0,
                "RUB"
            ],
            [
                "XS0191754729",
                "PTOD",
                "РПС с ЦК: Облигации (USD) - адрес.",
                283,
                4,
                "ndm",
                1,
                "stock",
                0,
                4,
                "2017-02-21",
                "2022-10-07",
                "2016-01-25",
                "2022-10-26",
                0,
                "USD"
            ],
            [
                "XS0191754729",
                "CTOB",
                "РПС с ЦК Нерезиденты: Облигации - адрес.",
                1062,
                1015,
                "nonresndm",
                1,
                "stock",
                0,
                4,
                null,
                null,
                "2022-06-27",
                "2022-10-26",
                0,
                "RUB"
            ],
            [
                "XS0191754729",
                "CTOD",
                "РПС с ЦК Нерезиденты: Облигации (USD) - адрес.",
                1066,
                1015,
                "nonresndm",
                1,
                "stock",
                0,
                4,
                null,
                null,
                "2022-06-27",
                "2022-10-26",
                0,
                "USD"
            ],
            [
                "XS0191754729",
                "CPMO",
                "РЕПО-M Нерезиденты - адрес.",
                1071,
                1017,
                "nonresrepo",
                1,
                "stock",
                0,
                6,
                null,
                null,
                "2022-06-27",
                "2022-10-26",
                0,
                "RUB"
            ],
            [
                "XS0191754729",
                "CPEU",
                "РЕПО-M Нерезиденты (USD) - адрес.",
                1073,
                1017,
                "nonresrepo",
                1,
                "stock",
                0,
                6,
                null,
                null,
                "2022-06-27",
                "2022-10-26",
                0,
                "USD"
            ],
            [
                "XS0191754729",
                "CPEO",
                "РЕПО-M Нерезиденты (EUR) - адрес.",
                1075,
                1017,
                "nonresrepo",
                1,
                "stock",
                0,
                6,
                null,
                null,
                "2022-06-27",
                "2022-10-26",
                0,
                "EUR"
            ],
            [
                "XS0191754729",
                "CPEY",
                "РЕПО-M Нерезиденты (CNY) - адрес.",
                1077,
                1017,
                "nonresrepo",
                1,
                "stock",
                0,
                6,
                null,
                null,
                "2022-09-26",
                "2022-10-26",
                0,
                "CNY"
            ],
            [
                "XS0191754729",
                "OCBR",
                "OTC: Облигации с ЦК - двусторонние",
                1017,
                1014,
                "ndm",
                1012,
                "otc",
                1,
                4,
                "2022-08-15",
                "2022-09-13",
                "2022-04-25",
                "2024-10-10",
                1,
                "RUB"
            ],
            [
                "XS0191754729",
                "OCBU",
                "OTC: Облигации с ЦК (USD) - двусторонние",
                1019,
                1014,
                "ndm",
                1012,
                "otc",
                1,
                4,
                "2022-06-27",
                "2022-09-21",
                "2022-04-25",
                "2024-10-10",
                0,
                "USD"
            ],
            [
                "XS0191754729",
                "OCBY",
                "OTC: Облигации с ЦК (CNY) - двусторонние",
                1204,
                1014,
                "ndm",
                1012,
                "otc",
                1,
                4,
                null,
                null,
                "2023-03-27",
                "2024-10-10",
                0,
                "CNY"
            ],
            [
                "XS0191754729",
                "OCAR",
                "OTC: Облигации с ЦК адрес. - двусторонние",
                1263,
                1014,
                "ndm",
                1012,
                "otc",
                1,
                4,
                null,
                null,
                "2023-04-10",
                "2024-10-10",
                0,
                "RUB"
            ],
            [
                "XS0191754729",
                "OCAY",
                "OTC: Облигации с ЦК адрес. (CNY) - двусторонние",
                1265,
                1014,
                "ndm",
                1012,
                "otc",
                1,
                4,
                null,
                null,
                "2023-04-10",
                "2024-10-10",
                0,
                "CNY"
            ],
            [
                "XS0191754729",
                "OCAU",
                "OTC: Облигации с ЦК адрес. (USD) - двусторонние",
                1267,
                1014,
                "ndm",
                1012,
                "otc",
                1,
                4,
                null,
                null,
                "2023-04-10",
                "2024-10-10",
                0,
                "USD"
            ],
            [
                "XS0191754729",
                "RPMO",
                "РЕПО-М - адрес.",
                201,
                3,
                "repo",
                1,
                "stock",
                0,
                6,
                "2015-03-10",
                "2020-03-10",
                "2014-06-27",
                "2022-10-26",
                0,
                "RUB"
            ],
            [
                "XS0191754729",
                "EQRP",
                "РЕПО с ЦК 1 день - безадрес.",
                50,
                27,
                "ccp",
                1,
                "stock",
                1,
                4,
                "2015-12-10",
                "2022-10-13",
                "2014-12-26",
                "2024-10-10",
                0,
                "RUB"
            ],
            [
                "XS0191754729",
                "EQRD",
                "РЕПО с ЦК 1 день (USD) - безадрес.",
                92,
                27,
                "ccp",
                1,
                "stock",
                1,
                4,
                "2015-11-19",
                "2022-09-28",
                "2015-06-01",
                "2024-10-10",
                0,
                "USD"
            ],
            [
                "XS0191754729",
                "EQRE",
                "РЕПО с ЦК 1 день (EUR) - безадрес.",
                93,
                27,
                "ccp",
                1,
                "stock",
                1,
                4,
                null,
                null,
                "2015-06-01",
                "2024-10-10",
                0,
                "EUR"
            ],
            [
                "XS0191754729",
                "EQRY",
                "РЕПО с ЦК 1 день (CNY) - безадрес.",
                152,
                27,
                "ccp",
                1,
                "stock",
                1,
                4,
                null,
                null,
                "2019-03-07",
                "2024-10-10",
                0,
                "CNY"
            ],
            [
                "XS0191754729",
                "EQWP",
                "РЕПО с ЦК 7 дн. - безадрес.",
                76,
                27,
                "ccp",
                1,
                "stock",
                1,
                4,
                "2017-12-28",
                "2019-12-30",
                "2015-06-01",
                "2024-10-10",
                0,
                "RUB"
            ],
            [
                "XS0191754729",
                "EQWD",
                "РЕПО с ЦК 7 дней (USD) - безадрес.",
                78,
                27,
                "ccp",
                1,
                "stock",
                1,
                4,
                "2018-03-06",
                "2021-12-27",
                "2016-01-26",
                "2024-10-10",
                0,
                "USD"
            ],
            [
                "XS0191754729",
                "EQWE",
                "РЕПО с ЦК 7 дней (EUR) - безадрес.",
                79,
                27,
                "ccp",
                1,
                "stock",
                1,
                4,
                null,
                null,
                "2016-01-26",
                "2024-10-10",
                0,
                "EUR"
            ],
            [
                "XS0191754729",
                "EQWY",
                "РЕПО с ЦК 7 дней (CNY) - безадрес.",
                1116,
                27,
                "ccp",
                1,
                "stock",
                1,
                4,
                null,
                null,
                "2022-09-26",
                "2024-10-10",
                0,
                "CNY"
            ],
            [
                "XS0191754729",
                "LIQR",
                "РЕПО с ЦК: Урегулирование - безадрес.",
                148,
                27,
                "ccp",
                1,
                "stock",
                1,
                4,
                "2021-07-07",
                "2021-07-07",
                "2019-03-04",
                "2024-10-10",
                0,
                null
            ],
            [
                "XS0191754729",
                "PSRP",
                "РЕПО с ЦК - адрес.",
                65,
                27,
                "ccp",
                1,
                "stock",
                1,
                4,
                "2015-03-16",
                "2022-10-07",
                "2014-12-26",
                "2024-10-10",
                0,
                "RUB"
            ],
            [
                "XS0191754729",
                "PSRD",
                "РЕПО с ЦК (USD) - адрес.",
                91,
                27,
                "ccp",
                1,
                "stock",
                1,
                4,
                "2015-09-17",
                "2022-03-15",
                "2015-06-01",
                "2024-10-10",
                0,
                "USD"
            ],
            [
                "XS0191754729",
                "PSRE",
                "РЕПО с ЦК (EUR) - адрес.",
                96,
                27,
                "ccp",
                1,
                "stock",
                1,
                4,
                "2017-12-18",
                "2022-03-16",
                "2015-06-01",
                "2024-10-10",
                0,
                "EUR"
            ],
            [
                "XS0191754729",
                "PSRY",
                "РЕПО с ЦК (CNY) - адрес.",
                153,
                27,
                "ccp",
                1,
                "stock",
                1,
                4,
                null,
                null,
                "2019-03-07",
                "2024-10-10",
                0,
                "CNY"
            ],
            [
                "XS0191754729",
                "CIQR",
                "Урегулирование РЕПО с ЦК Нерезиденты - безадрес.",
                1080,
                1019,
                "nonresccp",
                1,
                "stock",
                1,
                4,
                null,
                null,
                "2022-06-27",
                "2024-10-10",
                0,
                null
            ],
            [
                "XS0191754729",
                "CIQB",
                "Урегулирование с ЦК Нерезиденты - безадрес.",
                1082,
                36,
                "mamc",
                1,
                "stock",
                0,
                4,
                null,
                null,
                "2022-06-27",
                "2023-04-10",
                0,
                null
            ],
            [
                "XS0191754729",
                "OBBO",
                "ОТС-система: облигации",
                141,
                39,
                "bonds",
                7,
                "offboard",
                0,
                2,
                "2018-11-08",
                "2020-03-17",
                "2018-11-08",
                "2022-10-26",
                0,
                null
            ],
            [
                "XS0191754729",
                "QBND",
                "Квоты",
                1280,
                1279,
                "bonds",
                1282,
                "quotes",
                1,
                4,
                null,
                null,
                "2023-06-05",
                "2024-10-10",
                0,
                null
            ]
        ]
    }
}