{
    "description": {
        "columns": [
            "name",
            "title",
            "value",
            "type",
            "sort_order",
            "is_hidden",
            "precision"
        ],
        "data": [
            [
                "SECID",
                "Код ценной бумаги",
                "GOOD",
                "string",
                1,
                0,
                null
            ],
            [
                "NAME",
                "Полное наименование",
                "ДОХОДЪ Стратегии денеж. рынка",
                "string",
                3,
                0,
                null
            ],
            [
                "SHORTNAME",
                "Краткое наименование",
                "GOOD ETF",
                "string",
                4,
                0,
                null
            ],
            [
                "REGNUMBER",
                "Номер государственной регистрации",
                "6720",
                "string",
                5,
                0,
                null
            ],
            [
                "ISIN",
                "ISIN код",
                "RU000A10A7V4",
                "string",
                6,
                0,
                null
            ],
            [
                "LATNAME",
                "Английское наименование",
                "GOOD ETF DOHOD MM Strategies",
                "string",
                7,
                1,
                null
            ],
            [
                "ISSUEDATE",
                "Дата начала торгов",
                "2024-12-11",
                "date",
                8,
                0,
                null
            ],
            [
                "LISTLEVEL",
                "Уровень листинга",
                "1",
                "number",
                15,
                0,
                0
            ],
            [
                "ISQUALIFIEDINVESTORS",
                "Бумаги для квалифицированных инвесторов",
                "0",
                "boolean",
                16,
                0,
                0
            ],
            [
                "EVENINGSESSION",
                "Допуск к вечерней дополнительной торговой сессии",
                "1",
                "boolean",
                19,
                0,
                0
            ],
            [
                "TYPENAME",
                "Вид/категория ценной бумаги",
                "Пай биржевого ПИФа",
                "string",
                9000,
                0,
                null
            ],
            [
                "GROUP",
                "Код типа инструмента",
                "stock_ppif",
                "string",
                9001,
                1,
                null
            ],
            [
                "TYPE",
                "Тип бумаги",
                "exchange_ppif",
                "string",
                10000,
                1,
                null
            ],
            [
                "GROUPNAME",
                "Типа инструмента",
                "Паи ПИФов",
                "string",
                10011,
                1,
                null
            ],
            [
                "EMITTER_ID",
                "Код эмитента",
                "658",
                "number",
                11000,
                1,
                null
            ]
        ]
    },
    "boards": {
        "columns": [
            "secid",
            "boardid",
            "title",
            "board_group_id",
            "market_id",
            "market",
            "engine_id",
            "engine",
            "is_traded",
            "decimals",
            "history_from",
            "history_till",
            "listed_from",
            "listed_till",
            "is_primary",
            "currencyid",
            "unit"
        ],
        "data": [
            [
                "GOOD",
                "TQTF",
                "Т+: ETF - безадрес.",
                57,
                1,
                "shares",
                1,
                "stock",
                1,
                1,
                "2024-12-11",
                "2024-12-11",
                "2024-12-11",
                "2024-12-12",
                1,
                "RUB",
                "M"
            ],
            [
                "GOOD",
                "LIQB",
                "Продажа обеспечения бирж.рынок - безадрес.",
                120,
                36,
                "mamc",
                1,
                "stock",
                1,
                1,
                null,
                null,
                "2024-12-11",
                "2024-12-12",
                0,
                null,
                "M"
            ],
            [
                "GOOD",
                "RPEY",
                "РЕПО в ин.валюте (CNY) - адрес.",
                2,
                3,
                "repo",
                1,
                "stock",
                1,
                4,
                null,
                null,
                "2024-12-11",
                "2024-12-12",
                0,
                "CNY",
                "%"
            ],
            [
                "GOOD",
                "PTTF",
                "РПС с ЦК: ETF - адрес.",
                59,
                4,
                "ndm",
                1,
                "stock",
                1,
                1,
                null,
                null,
                "2024-12-11",
                "2024-12-12",
                0,
                "RUB",
                "M"
            ],
            [
                "GOOD",
                "PSTF",
                "РПС: ETF - адрес.",
                8,
                4,
                "ndm",
                1,
                "stock",
                1,
                1,
                null,
                null,
                "2024-12-11",
                "2024-12-12",
                0,
                "RUB",
                "M"
            ],
            [
                "GOOD",
                "CTEQ",
                "РПС с ЦК Нерезиденты: Акции и ДР - адрес.",
                1056,
                1015,
                "nonresndm",
                1,
                "stock",
                1,
                1,
                null,
                null,
                "2024-12-11",
                "2024-12-12",
                0,
                "RUB",
                "M"
            ],
            [
                "GOOD",
                "CPMO",
                "РЕПО-M Нерезиденты - адрес.",
                1071,
                1017,
                "nonresrepo",
                1,
                "stock",
                1,
                4,
                null,
                null,
                "2024-12-11",
                "2024-12-12",
                0,
                "RUB",
                "%"
            ],
            [
                "GOOD",
                "CPEY",
                "РЕПО-M Нерезиденты (CNY) - адрес.",
                1077,
                1017,
                "nonresrepo",
                1,
                "stock",
                1,
                4,
                null,
                null,
                "2024-12-11",
                "2024-12-12",
                0,
                "CNY",
                "%"
            ],
            [
                "GOOD",
                "RPMO",
                "РЕПО-М - адрес.",
                201,
                3,
                "repo",
                1,
                "stock",
                1,
                4,
                null,
                null,
                "2024-12-11",
                "2024-12-12",
                0,
                "RUB",
                "%"
            ],
            [
                "GOOD",
                "EQRP",
                "РЕПО с ЦК 1 день - безадрес.",
                50,
                27,
                "ccp",
                1,
                "stock",
                1,
                4,
                null,
                null,
                "2024-12-11",
                "2024-12-12",
                0,
                "RUB",
                "%"
            ],
            [
                "GOOD",
                "EQRY",
                "РЕПО с ЦК 1 день (CNY) - безадрес.",
                152,
                27,
                "ccp",
                1,
                "stock",
                1,
                4,
                null,
                null,
                "2024-12-11",
                "2024-12-12",
                0,
                "CNY",
                "%"
            ],
            [
                "GOOD",
                "EQWP",
                "РЕПО с ЦК 7 дн. - безадрес.",
                76,
                27,
                "ccp",
                1,
                "stock",
                1,
                4,
                null,
                null,
                "2024-12-11",
                "2024-12-12",
                0,
                "RUB",
                "%"
            ],
            [
                "GOOD",
                "EQWY",
                "РЕПО с ЦК 7 дней (CNY) - безадрес.",
                1116,
                27,
                "ccp",
                1,
                "stock",
                1,
                4,
                null,
                null,
                "2024-12-11",
                "2024-12-12",
                0,
                "CNY",
                "%"
            ],
            [
                "GOOD",
                "LIQR",
                "РЕПО с ЦК: Урегулирование - безадрес.",
                148,
                27,
                "ccp",
                1,
                "stock",
                1,
                4,
                null,
                null,
                "2024-12-11",
                "2024-12-12",
                0,
                null,
                "%"
            ],
            [
                "GOOD",
                "PSRP",
                "РЕПО с ЦК - адрес.",
                65,
                27,
                "ccp",
                1,
                "stock",
                1,
                4,
                null,
                null,
                "2024-12-11",
                "2024-12-12",
                0,
                "RUB",
                "%"
            ],
            [
                "GOOD",
                "PSRY",
                "РЕПО с ЦК (CNY) - адрес.",
                153,
                27,
                "ccp",
                1,
                "stock",
                1,
                4,
                null,
                null,
                "2024-12-11",
                "2024-12-12",
                0,
                "CNY",
                "%"
            ],
            [
                "GOOD",
                "CIQR",
                "Урегулирование РЕПО с ЦК Нерезиденты - безадрес.",
                1080,
                1019,
                "nonresccp",
                1,
                "stock",
                1,
                4,
                null,
                null,
                "2024-12-11",
                "2024-12-12",
                0,
                null,
                "%"
            ],
            [
                "GOOD",
                "CIQB",
                "Урегулирование с ЦК Нерезиденты - безадрес.",
                1082,
                36,
                "mamc",
                1,
                "stock",
                1,
                1,
                null,
                null,
                "2024-12-11",
                "2024-12-12",
                0,
                null,
                "M"
            ]
        ]
    }
}