{
    "description": {
        "columns": [
            "name",
            "title",
            "value",
            "type",
            "sort_order",
            "is_hidden",
            "precision"
        ],
        "data": [
            [
                "SECID",
                "Код ценной бумаги",
                "YNDX",
                "string",
                1,
                0,
                null
            ],
            [
                "NAME",
                "Полное наименование",
                "PLLC Yandex N.V. class A shs",
                "string",
                3,
                0,
                null
            ],
            [
                "SHORTNAME",
                "Краткое наименование",
                "Yandex clA",
                "string",
                4,
                0,
                null
            ],
            [
                "ISIN",
                "ISIN код",
                "NL0009805522",
                "string",
                5,
                0,
                null
            ],
            [
                "ISSUESIZE",
                "Объем выпуска",
                "326342270",
                "number",
                7,
                0,
                0
            ],
            [
                "FACEVALUE",
                "Номинальная стоимость",
                "0.01",
                "number",
                8,
                0,
                2
            ],
            [
                "FACEUNIT",
                "Валюта номинала",
                "EUR",
                "string",
                9,
                0,
                null
            ],
            [
                "ISSUEDATE",
                "Дата начала торгов",
                "2014-06-04",
                "date",
                10,
                0,
                null
            ],
            [
                "LATNAME",
                "Английское наименование",
                "PLLC Yandex N.V.",
                "string",
                11,
                1,
                null
            ],
            [
                "LISTLEVEL",
                "Уровень листинга",
                "1",
                "number",
                18,
                0,
                0
            ],
            [
                "INCLUDEDBYMOEX",
                "ИЦБ допущена к орг. торгам по инициативе биржи",
                "0",
                "boolean",
                19,
                0,
                0
            ],
            [
                "ISQUALIFIEDINVESTORS",
                "Бумаги для квалифицированных инвесторов",
                "0",
                "boolean",
                20,
                0,
                0
            ],
            [
                "MORNINGSESSION",
                "Допуск к утренней дополнительной торговой сессии",
                "1",
                "boolean",
                23,
                0,
                0
            ],
            [
                "EVENINGSESSION",
                "Допуск к вечерней дополнительной торговой сессии",
                "1",
                "boolean",
                24,
                0,
                0
            ],
            [
                "TYPENAME",
                "Вид/категория ценной бумаги",
                "Акция обыкновенная",
                "string",
                9000,
                0,
                null
            ],
            [
                "GROUP",
                "Код типа инструмента",
                "stock_shares",
                "string",
                9001,
                1,
                null
            ],
            [
                "TYPE",
                "Тип бумаги",
                "common_share",
                "string",
                10000,
                1,
                null
            ],
            [
                "GROUPNAME",
                "Типа инструмента",
                "Акции",
                "string",
                10011,
                1,
                null
            ],
            [
                "EMITTER_ID",
                "Код эмитента",
                "6822",
                "number",
                11000,
                1,
                null
            ]
        ]
    },
    "boards": {
        "columns": [
            "secid",
            "boardid",
            "title",
            "board_group_id",
            "market_id",
            "market",
            "engine_id",
            "engine",
            "is_traded",
            "decimals",
            "history_from",
            "history_till",
            "listed_from",
            "listed_till",
            "is_primary",
            "currencyid"
        ],
        "data": [
            [
                "YNDX",
                "TQBR",
                "Т+: Акции и ДР - безадрес.",
                57,
                1,
                "shares",
                1,
                "stock",
                0,
                1,
                "2014-06-04",
                "2024-07-09",
                "2014-06-04",
                "2024-07-09",
                1,
                "RUB"
            ],
            [
                "YNDX",
                "TQDP",
                "Крупные пакеты - Акции - безадрес.",
                42,
                1,
                "shares",
                1,
                "stock",
                0,
                1,
                null,
                null,
                "2019-03-04",
                "2023-02-15",
                0,
                "RUB"
            ],
            [
                "YNDX",
                "EQDP",
                "Крупные пакеты - Акции - безадрес.",
                42,
                1,
                "shares",
                1,
                "stock",
                0,
                1,
                "2017-04-19",
                "2019-03-01",
                "2017-04-19",
                "2019-03-01",
                0,
                "RUB"
            ],
            [
                "YNDX",
                "LIQB",
                "Продажа обеспечения бирж.рынок - безадрес.",
                120,
                36,
                "mamc",
                1,
                "stock",
                0,
                6,
                null,
                null,
                "2018-05-21",
                "2024-07-09",
                0,
                null
            ],
            [
                "YNDX",
                "RPEY",
                "РЕПО в ин.валюте (CNY) - адрес.",
                2,
                3,
                "repo",
                1,
                "stock",
                0,
                4,
                null,
                null,
                "2022-09-26",
                "2024-07-09",
                0,
                "CNY"
            ],
            [
                "YNDX",
                "RPMA",
                "РЕПО c акциями - адрес.",
                95,
                3,
                "repo",
                1,
                "stock",
                0,
                4,
                "2014-06-24",
                "2019-04-19",
                "2014-06-04",
                "2020-03-04",
                0,
                "RUB"
            ],
            [
                "YNDX",
                "RPEU",
                "РЕПО в ин. валюте (USD) - адрес.",
                94,
                3,
                "repo",
                1,
                "stock",
                0,
                4,
                "2017-12-28",
                "2022-02-03",
                "2017-04-11",
                "2024-07-09",
                0,
                "USD"
            ],
            [
                "YNDX",
                "RPEO",
                "РЕПО в ин. валюте (EUR) - адрес.",
                90,
                3,
                "repo",
                1,
                "stock",
                0,
                4,
                "2020-03-19",
                "2020-06-22",
                "2017-04-11",
                "2024-07-09",
                0,
                "EUR"
            ],
            [
                "YNDX",
                "SPEQ",
                "Поставка по СК (акции)",
                125,
                1,
                "shares",
                1,
                "stock",
                0,
                6,
                "2020-04-06",
                "2024-05-24",
                "2020-04-06",
                "2024-07-09",
                0,
                "RUB"
            ],
            [
                "YNDX",
                "SOTC",
                "Репортинг внебиржевых сделок (6264-У)",
                71,
                29,
                "otc",
                1,
                "stock",
                0,
                5,
                "2014-07-02",
                "2022-12-02",
                "2014-06-06",
                "2022-12-03",
                0,
                null
            ],
            [
                "YNDX",
                "MXBD",
                "MOEX Board",
                72,
                33,
                "moexboard",
                1,
                "stock",
                0,
                4,
                "2020-08-25",
                "2024-09-13",
                "2020-08-25",
                "2024-09-13",
                0,
                null
            ],
            [
                "YNDX",
                "PTEQ",
                "РПС с ЦК: Акции и ДР - адрес.",
                59,
                4,
                "ndm",
                1,
                "stock",
                0,
                1,
                "2014-06-05",
                "2024-06-11",
                "2014-06-04",
                "2024-07-09",
                0,
                "RUB"
            ],
            [
                "YNDX",
                "PSEQ",
                "РПС: Акции - адрес.",
                8,
                4,
                "ndm",
                1,
                "stock",
                0,
                1,
                "2014-06-11",
                "2024-06-03",
                "2014-06-04",
                "2024-07-09",
                0,
                "RUB"
            ],
            [
                "YNDX",
                "PSBB",
                "Выкуп - адрес.",
                108,
                4,
                "ndm",
                1,
                "stock",
                0,
                1,
                "2024-05-14",
                "2024-07-09",
                "2024-05-14",
                "2024-07-09",
                0,
                "RUB"
            ],
            [
                "YNDX",
                "CTEQ",
                "РПС с ЦК Нерезиденты: Акции и ДР - адрес.",
                1056,
                1015,
                "nonresndm",
                1,
                "stock",
                0,
                1,
                null,
                null,
                "2022-06-27",
                "2024-07-09",
                0,
                "RUB"
            ],
            [
                "YNDX",
                "CPMO",
                "РЕПО-M Нерезиденты - адрес.",
                1071,
                1017,
                "nonresrepo",
                1,
                "stock",
                0,
                4,
                null,
                null,
                "2022-06-27",
                "2024-07-09",
                0,
                "RUB"
            ],
            [
                "YNDX",
                "CPEU",
                "РЕПО-M Нерезиденты (USD) - адрес.",
                1073,
                1017,
                "nonresrepo",
                1,
                "stock",
                0,
                4,
                null,
                null,
                "2022-06-27",
                "2024-07-09",
                0,
                "USD"
            ],
            [
                "YNDX",
                "CPEO",
                "РЕПО-M Нерезиденты (EUR) - адрес.",
                1075,
                1017,
                "nonresrepo",
                1,
                "stock",
                0,
                4,
                null,
                null,
                "2022-06-27",
                "2024-07-09",
                0,
                "EUR"
            ],
            [
                "YNDX",
                "CPEY",
                "РЕПО-M Нерезиденты (CNY) - адрес.",
                1077,
                1017,
                "nonresrepo",
                1,
                "stock",
                0,
                4,
                null,
                null,
                "2022-09-26",
                "2024-07-09",
                0,
                "CNY"
            ],
            [
                "YNDX",
                "MPTR",
                "ОТС: Акции РПС с ЦК - адресные",
                1260,
                1262,
                "sharesndm",
                1012,
                "otc",
                0,
                1,
                "2023-04-27",
                "2024-05-08",
                "2023-04-10",
                "2024-07-09",
                0,
                "RUB"
            ],
            [
                "YNDX",
                "RPMO",
                "РЕПО-М - адрес.",
                201,
                3,
                "repo",
                1,
                "stock",
                0,
                4,
                "2019-04-22",
                "2024-06-13",
                "2019-04-22",
                "2024-07-09",
                0,
                "RUB"
            ],
            [
                "YNDX",
                "EQRP",
                "РЕПО с ЦК 1 день - безадрес.",
                50,
                27,
                "ccp",
                1,
                "stock",
                0,
                3,
                "2014-11-17",
                "2024-06-13",
                "2014-11-10",
                "2024-07-09",
                0,
                "RUB"
            ],
            [
                "YNDX",
                "EQRD",
                "РЕПО с ЦК 1 день (USD) - безадрес.",
                92,
                27,
                "ccp",
                1,
                "stock",
                0,
                4,
                "2017-12-05",
                "2022-05-12",
                "2015-06-01",
                "2024-07-09",
                0,
                "USD"
            ],
            [
                "YNDX",
                "EQRE",
                "РЕПО с ЦК 1 день (EUR) - безадрес.",
                93,
                27,
                "ccp",
                1,
                "stock",
                0,
                4,
                "2021-09-28",
                "2021-09-28",
                "2015-06-01",
                "2024-07-09",
                0,
                "EUR"
            ],
            [
                "YNDX",
                "EQRY",
                "РЕПО с ЦК 1 день (CNY) - безадрес.",
                152,
                27,
                "ccp",
                1,
                "stock",
                0,
                4,
                null,
                null,
                "2019-03-07",
                "2024-07-09",
                0,
                "CNY"
            ],
            [
                "YNDX",
                "EQWP",
                "РЕПО с ЦК 7 дн. - безадрес.",
                76,
                27,
                "ccp",
                1,
                "stock",
                0,
                3,
                "2015-10-22",
                "2022-12-30",
                "2015-06-01",
                "2024-07-09",
                0,
                "RUB"
            ],
            [
                "YNDX",
                "EQWD",
                "РЕПО с ЦК 7 дней (USD) - безадрес.",
                78,
                27,
                "ccp",
                1,
                "stock",
                0,
                4,
                null,
                null,
                "2016-01-26",
                "2024-07-09",
                0,
                "USD"
            ],
            [
                "YNDX",
                "EQWE",
                "РЕПО с ЦК 7 дней (EUR) - безадрес.",
                79,
                27,
                "ccp",
                1,
                "stock",
                0,
                4,
                null,
                null,
                "2016-01-26",
                "2024-07-09",
                0,
                "EUR"
            ],
            [
                "YNDX",
                "EQWY",
                "РЕПО с ЦК 7 дней (CNY) - безадрес.",
                1116,
                27,
                "ccp",
                1,
                "stock",
                0,
                4,
                null,
                null,
                "2022-09-26",
                "2024-07-09",
                0,
                "CNY"
            ],
            [
                "YNDX",
                "LIQR",
                "РЕПО с ЦК: Урегулирование - безадрес.",
                148,
                27,
                "ccp",
                1,
                "stock",
                0,
                2,
                "2019-12-04",
                "2023-01-04",
                "2019-03-04",
                "2024-07-09",
                0,
                null
            ],
            [
                "YNDX",
                "PSRP",
                "РЕПО с ЦК - адрес.",
                65,
                27,
                "ccp",
                1,
                "stock",
                0,
                2,
                "2014-11-12",
                "2024-06-14",
                "2014-11-10",
                "2024-07-09",
                0,
                "RUB"
            ],
            [
                "YNDX",
                "PSRD",
                "РЕПО с ЦК (USD) - адрес.",
                91,
                27,
                "ccp",
                1,
                "stock",
                0,
                4,
                "2017-04-20",
                "2024-02-26",
                "2015-06-01",
                "2024-07-09",
                0,
                "USD"
            ],
            [
                "YNDX",
                "PSRE",
                "РЕПО с ЦК (EUR) - адрес.",
                96,
                27,
                "ccp",
                1,
                "stock",
                0,
                4,
                "2020-04-22",
                "2023-11-30",
                "2015-06-01",
                "2024-07-09",
                0,
                "EUR"
            ],
            [
                "YNDX",
                "PSRY",
                "РЕПО с ЦК (CNY) - адрес.",
                153,
                27,
                "ccp",
                1,
                "stock",
                0,
                4,
                "2023-09-13",
                "2024-05-17",
                "2019-03-07",
                "2024-07-09",
                0,
                "CNY"
            ],
            [
                "YNDX",
                "CIQR",
                "Урегулирование РЕПО с ЦК Нерезиденты - безадрес.",
                1080,
                1019,
                "nonresccp",
                1,
                "stock",
                0,
                2,
                null,
                null,
                "2022-06-27",
                "2024-07-09",
                0,
                null
            ],
            [
                "YNDX",
                "CIQB",
                "Урегулирование с ЦК Нерезиденты - безадрес.",
                1082,
                36,
                "mamc",
                1,
                "stock",
                0,
                6,
                null,
                null,
                "2022-06-27",
                "2024-07-09",
                0,
                null
            ],
            [
                "YNDX",
                "CLMR",
                "Classica - безадрес.",
                43,
                25,
                "classica",
                1,
                "stock",
                0,
                3,
                null,
                null,
                "2014-06-04",
                "2014-07-25",
                0,
                "RUB"
            ]
        ]
    }
}