{
    "description": {
        "columns": [
            "name",
            "title",
            "value",
            "type",
            "sort_order",
            "is_hidden",
            "precision"
        ],
        "data": [
            [
                "SECID",
                "Код ценной бумаги",
                "TEMS",
                "string",
                1,
                0,
                null
            ],
            [
                "NAME",
                "Полное наименование",
                "ТИНЬКОФФ РАЗВИВАЮЩИЕСЯ РЫНКИ",
                "string",
                3,
                0,
                null
            ],
            [
                "SHORTNAME",
                "Краткое наименование",
                "TEMS ETF",
                "string",
                4,
                0,
                null
            ],
            [
                "REGNUMBER",
                "Номер государственной регистрации",
                "4630",
                "string",
                5,
                0,
                null
            ],
            [
                "ISIN",
                "ISIN код",
                "RU000A103VJ5",
                "string",
                6,
                0,
                null
            ],
            [
                "LATNAME",
                "Английское наименование",
                "TEMS TINKOFF EMERGING MARKETS",
                "string",
                7,
                1,
                null
            ],
            [
                "ISSUEDATE",
                "Дата начала торгов",
                "2021-10-29",
                "date",
                8,
                0,
                null
            ],
            [
                "LISTLEVEL",
                "Уровень листинга",
                "1",
                "number",
                15,
                0,
                0
            ],
            [
                "ISQUALIFIEDINVESTORS",
                "Бумаги для квалифицированных инвесторов",
                "0",
                "boolean",
                16,
                0,
                0
            ],
            [
                "TYPENAME",
                "Вид/категория ценной бумаги",
                "Пай биржевого ПИФа",
                "string",
                9000,
                0,
                null
            ],
            [
                "GROUP",
                "Код типа инструмента",
                "stock_ppif",
                "string",
                9001,
                1,
                null
            ],
            [
                "TYPE",
                "Тип бумаги",
                "exchange_ppif",
                "string",
                10000,
                1,
                null
            ],
            [
                "GROUPNAME",
                "Типа инструмента",
                "Паи ПИФов",
                "string",
                10011,
                1,
                null
            ],
            [
                "EMITTER_ID",
                "Код эмитента",
                "10779",
                "number",
                11000,
                1,
                null
            ]
        ]
    },
    "boards": {
        "columns": [
            "secid",
            "boardid",
            "title",
            "board_group_id",
            "market_id",
            "market",
            "engine_id",
            "engine",
            "is_traded",
            "decimals",
            "history_from",
            "history_till",
            "listed_from",
            "listed_till",
            "is_primary",
            "currencyid"
        ],
        "data": [
            [
                "TEMS",
                "TQTF",
                "Т+: ETF - безадрес.",
                57,
                1,
                "shares",
                1,
                "stock",
                0,
                2,
                "2021-10-29",
                "2024-08-21",
                "2021-10-29",
                "2024-08-21",
                1,
                "RUB"
            ],
            [
                "TEMS",
                "TQTD",
                "Т+: ETF (USD) - безадрес.",
                156,
                1,
                "shares",
                1,
                "stock",
                0,
                4,
                "2021-10-29",
                "2024-08-21",
                "2021-10-29",
                "2024-08-21",
                0,
                "USD"
            ],
            [
                "TEMS",
                "LIQB",
                "Продажа обеспечения бирж.рынок - безадрес.",
                120,
                36,
                "mamc",
                1,
                "stock",
                0,
                2,
                null,
                null,
                "2021-10-29",
                "2024-08-21",
                0,
                null
            ],
            [
                "TEMS",
                "RPEY",
                "РЕПО в ин.валюте (CNY) - адрес.",
                2,
                3,
                "repo",
                1,
                "stock",
                0,
                4,
                null,
                null,
                "2022-09-26",
                "2024-08-21",
                0,
                "CNY"
            ],
            [
                "TEMS",
                "RPEU",
                "РЕПО в ин. валюте (USD) - адрес.",
                94,
                3,
                "repo",
                1,
                "stock",
                0,
                4,
                "2022-01-04",
                "2022-01-19",
                "2021-10-29",
                "2024-08-21",
                0,
                "USD"
            ],
            [
                "TEMS",
                "RPEO",
                "РЕПО в ин. валюте (EUR) - адрес.",
                90,
                3,
                "repo",
                1,
                "stock",
                0,
                4,
                null,
                null,
                "2021-10-29",
                "2024-08-21",
                0,
                "EUR"
            ],
            [
                "TEMS",
                "SOTC",
                "Репортинг внебиржевых сделок (6264-У)",
                71,
                29,
                "otc",
                1,
                "stock",
                0,
                5,
                "2021-10-22",
                "2022-06-30",
                "2021-10-22",
                "2022-06-30",
                0,
                null
            ],
            [
                "TEMS",
                "PTTF",
                "РПС с ЦК: ETF - адрес.",
                59,
                4,
                "ndm",
                1,
                "stock",
                0,
                2,
                null,
                null,
                "2021-10-29",
                "2024-08-21",
                0,
                "RUB"
            ],
            [
                "TEMS",
                "PTTD",
                "РПС с ЦК: ETF (USD) - адрес.",
                73,
                4,
                "ndm",
                1,
                "stock",
                0,
                4,
                "2022-07-20",
                "2022-07-20",
                "2021-10-29",
                "2024-08-21",
                0,
                "USD"
            ],
            [
                "TEMS",
                "PSTF",
                "РПС: ETF - адрес.",
                8,
                4,
                "ndm",
                1,
                "stock",
                0,
                2,
                null,
                null,
                "2021-10-29",
                "2024-08-21",
                0,
                "RUB"
            ],
            [
                "TEMS",
                "PSTD",
                "РПС: ETF (USD) - адрес.",
                74,
                4,
                "ndm",
                1,
                "stock",
                0,
                4,
                null,
                null,
                "2021-10-29",
                "2024-08-21",
                0,
                "USD"
            ],
            [
                "TEMS",
                "CTEQ",
                "РПС с ЦК Нерезиденты: Акции и ДР - адрес.",
                1056,
                1015,
                "nonresndm",
                1,
                "stock",
                0,
                2,
                null,
                null,
                "2022-06-27",
                "2024-08-21",
                0,
                "RUB"
            ],
            [
                "TEMS",
                "CTSD",
                "РПС с ЦК Нерезиденты: Акции и ДР (USD) - адрес.",
                1058,
                1015,
                "nonresndm",
                1,
                "stock",
                0,
                4,
                null,
                null,
                "2022-06-27",
                "2024-08-21",
                0,
                "USD"
            ],
            [
                "TEMS",
                "CPMO",
                "РЕПО-M Нерезиденты - адрес.",
                1071,
                1017,
                "nonresrepo",
                1,
                "stock",
                0,
                4,
                null,
                null,
                "2022-06-27",
                "2024-08-21",
                0,
                "RUB"
            ],
            [
                "TEMS",
                "CPEU",
                "РЕПО-M Нерезиденты (USD) - адрес.",
                1073,
                1017,
                "nonresrepo",
                1,
                "stock",
                0,
                4,
                null,
                null,
                "2022-06-27",
                "2024-08-21",
                0,
                "USD"
            ],
            [
                "TEMS",
                "CPEO",
                "РЕПО-M Нерезиденты (EUR) - адрес.",
                1075,
                1017,
                "nonresrepo",
                1,
                "stock",
                0,
                4,
                null,
                null,
                "2022-06-27",
                "2024-08-21",
                0,
                "EUR"
            ],
            [
                "TEMS",
                "CPEY",
                "РЕПО-M Нерезиденты (CNY) - адрес.",
                1077,
                1017,
                "nonresrepo",
                1,
                "stock",
                0,
                4,
                null,
                null,
                "2022-09-26",
                "2024-08-21",
                0,
                "CNY"
            ],
            [
                "TEMS",
                "RPMO",
                "РЕПО-М - адрес.",
                201,
                3,
                "repo",
                1,
                "stock",
                0,
                4,
                "2022-01-03",
                "2022-01-03",
                "2021-10-29",
                "2024-08-21",
                0,
                "RUB"
            ],
            [
                "TEMS",
                "EQRP",
                "РЕПО с ЦК 1 день - безадрес.",
                50,
                27,
                "ccp",
                1,
                "stock",
                0,
                4,
                "2023-09-19",
                "2023-09-25",
                "2021-10-29",
                "2024-08-21",
                0,
                "RUB"
            ],
            [
                "TEMS",
                "EQRD",
                "РЕПО с ЦК 1 день (USD) - безадрес.",
                92,
                27,
                "ccp",
                1,
                "stock",
                0,
                4,
                null,
                null,
                "2021-10-29",
                "2024-08-21",
                0,
                "USD"
            ],
            [
                "TEMS",
                "EQRE",
                "РЕПО с ЦК 1 день (EUR) - безадрес.",
                93,
                27,
                "ccp",
                1,
                "stock",
                0,
                4,
                null,
                null,
                "2021-10-29",
                "2024-08-21",
                0,
                "EUR"
            ],
            [
                "TEMS",
                "EQRY",
                "РЕПО с ЦК 1 день (CNY) - безадрес.",
                152,
                27,
                "ccp",
                1,
                "stock",
                0,
                4,
                null,
                null,
                "2021-10-29",
                "2024-08-21",
                0,
                "CNY"
            ],
            [
                "TEMS",
                "EQWP",
                "РЕПО с ЦК 7 дн. - безадрес.",
                76,
                27,
                "ccp",
                1,
                "stock",
                0,
                4,
                null,
                null,
                "2021-10-29",
                "2024-08-21",
                0,
                "RUB"
            ],
            [
                "TEMS",
                "EQWD",
                "РЕПО с ЦК 7 дней (USD) - безадрес.",
                78,
                27,
                "ccp",
                1,
                "stock",
                0,
                4,
                null,
                null,
                "2021-10-29",
                "2024-08-21",
                0,
                "USD"
            ],
            [
                "TEMS",
                "EQWE",
                "РЕПО с ЦК 7 дней (EUR) - безадрес.",
                79,
                27,
                "ccp",
                1,
                "stock",
                0,
                4,
                null,
                null,
                "2021-10-29",
                "2024-08-21",
                0,
                "EUR"
            ],
            [
                "TEMS",
                "EQWY",
                "РЕПО с ЦК 7 дней (CNY) - безадрес.",
                1116,
                27,
                "ccp",
                1,
                "stock",
                0,
                4,
                null,
                null,
                "2022-09-26",
                "2024-08-21",
                0,
                "CNY"
            ],
            [
                "TEMS",
                "LIQR",
                "РЕПО с ЦК: Урегулирование - безадрес.",
                148,
                27,
                "ccp",
                1,
                "stock",
                0,
                4,
                null,
                null,
                "2021-10-29",
                "2024-08-21",
                0,
                null
            ],
            [
                "TEMS",
                "PSRP",
                "РЕПО с ЦК - адрес.",
                65,
                27,
                "ccp",
                1,
                "stock",
                0,
                4,
                "2021-11-09",
                "2023-09-25",
                "2021-10-29",
                "2024-08-21",
                0,
                "RUB"
            ],
            [
                "TEMS",
                "PSRD",
                "РЕПО с ЦК (USD) - адрес.",
                91,
                27,
                "ccp",
                1,
                "stock",
                0,
                4,
                "2021-11-09",
                "2023-02-21",
                "2021-10-29",
                "2024-08-21",
                0,
                "USD"
            ],
            [
                "TEMS",
                "PSRE",
                "РЕПО с ЦК (EUR) - адрес.",
                96,
                27,
                "ccp",
                1,
                "stock",
                0,
                4,
                null,
                null,
                "2021-10-29",
                "2024-08-21",
                0,
                "EUR"
            ],
            [
                "TEMS",
                "PSRY",
                "РЕПО с ЦК (CNY) - адрес.",
                153,
                27,
                "ccp",
                1,
                "stock",
                0,
                4,
                null,
                null,
                "2021-10-29",
                "2024-08-21",
                0,
                "CNY"
            ],
            [
                "TEMS",
                "CIQR",
                "Урегулирование РЕПО с ЦК Нерезиденты - безадрес.",
                1080,
                1019,
                "nonresccp",
                1,
                "stock",
                0,
                4,
                null,
                null,
                "2022-06-27",
                "2024-08-21",
                0,
                null
            ],
            [
                "TEMS",
                "CIQB",
                "Урегулирование с ЦК Нерезиденты - безадрес.",
                1082,
                36,
                "mamc",
                1,
                "stock",
                0,
                2,
                null,
                null,
                "2022-06-27",
                "2024-08-21",
                0,
                null
            ]
        ]
    }
}