{
    "description": {
        "columns": [
            "name",
            "title",
            "value",
            "type",
            "sort_order",
            "is_hidden",
            "precision"
        ],
        "data": [
            [
                "SECID",
                "Код ценной бумаги",
                "RU000A0JQUD3",
                "string",
                1,
                0,
                null
            ],
            [
                "NAME",
                "Полное наименование",
                "ПИФ ТрастЮн-Земел ОООТрастЮнЭМ",
                "string",
                3,
                0,
                null
            ],
            [
                "SHORTNAME",
                "Краткое наименование",
                "ПИФТрЮЗем",
                "string",
                4,
                0,
                null
            ],
            [
                "REGNUMBER",
                "Номер государственной регистрации",
                "1636-94162980",
                "string",
                5,
                0,
                null
            ],
            [
                "ISIN",
                "ISIN код",
                "RU000A0JQUD3",
                "string",
                6,
                0,
                null
            ],
            [
                "LATNAME",
                "Английское наименование",
                "PIF TrastUnion - Zemelnii",
                "string",
                7,
                1,
                null
            ],
            [
                "ISSUEDATE",
                "Дата начала торгов",
                "2010-04-23",
                "date",
                8,
                0,
                null
            ],
            [
                "TYPENAME",
                "Вид/категория ценной бумаги",
                "Пай закрытого ПИФа",
                "string",
                9000,
                0,
                null
            ],
            [
                "GROUP",
                "Код типа инструмента",
                "stock_ppif",
                "string",
                9001,
                1,
                null
            ],
            [
                "TYPE",
                "Тип бумаги",
                "private_ppif",
                "string",
                10000,
                1,
                null
            ],
            [
                "GROUPNAME",
                "Типа инструмента",
                "Паи ПИФов",
                "string",
                10011,
                1,
                null
            ],
            [
                "EMITTER_ID",
                "Код эмитента",
                "4322",
                "number",
                11000,
                1,
                null
            ]
        ]
    },
    "boards": {
        "columns": [
            "secid",
            "boardid",
            "title",
            "board_group_id",
            "market_id",
            "market",
            "engine_id",
            "engine",
            "is_traded",
            "decimals",
            "history_from",
            "history_till",
            "listed_from",
            "listed_till",
            "is_primary",
            "currencyid"
        ],
        "data": [
            [
                "RU000A0JQUD3",
                "TQIF",
                "Т+: Паи - безадрес.",
                57,
                1,
                "shares",
                1,
                "stock",
                0,
                0,
                "2014-06-09",
                "2016-01-14",
                "2014-06-09",
                "2016-01-14",
                1,
                "RUB"
            ],
            [
                "RU000A0JQUD3",
                "TQNE",
                "Т+: Акции, паи и ДР внесписочные - безадрес.",
                57,
                1,
                "shares",
                1,
                "stock",
                0,
                1,
                "2013-09-02",
                "2014-06-06",
                "2013-09-02",
                "2014-06-06",
                0,
                "RUB"
            ],
            [
                "RU000A0JQUD3",
                "EQNE",
                "Основной режим: Акции и паи внесписочные - безадрес.",
                6,
                1,
                "shares",
                1,
                "stock",
                0,
                1,
                "2010-04-23",
                "2013-08-30",
                "2010-04-23",
                "2013-08-30",
                0,
                "RUB"
            ],
            [
                "RU000A0JQUD3",
                "PTIF",
                "РПС с ЦК: Паи - адрес.",
                59,
                4,
                "ndm",
                1,
                "stock",
                0,
                0,
                null,
                null,
                "2014-06-09",
                "2016-01-14",
                0,
                "RUB"
            ],
            [
                "RU000A0JQUD3",
                "PTNE",
                "РПС С ЦК: Акции, паи и ДР внесписочные - адрес.",
                59,
                4,
                "ndm",
                1,
                "stock",
                0,
                1,
                null,
                null,
                "2013-09-02",
                "2014-06-06",
                0,
                "RUB"
            ],
            [
                "RU000A0JQUD3",
                "PSIF",
                "РПС: Паи - адрес.",
                8,
                4,
                "ndm",
                1,
                "stock",
                0,
                0,
                null,
                null,
                "2014-06-09",
                "2016-01-14",
                0,
                "RUB"
            ],
            [
                "RU000A0JQUD3",
                "PSNE",
                "РПС: Акции, паи и ДР внесписочные - адрес.",
                8,
                4,
                "ndm",
                1,
                "stock",
                0,
                1,
                null,
                null,
                "2012-04-12",
                "2014-06-06",
                0,
                "RUB"
            ]
        ]
    }
}